{"cameraMode":{"drawMode":0,"name":"Shaded","section":"Shading Mode"},"sceneLighting":false,"audioPlay":false,"sceneViewState":{"m_AlwaysRefresh":true,"showFog":true,"showSkybox":false,"showFlares":true,"showImageEffects":true,"showParticleSystems":true,"showVisualEffectGraphs":true,"m_FxEnabled":true},"in2DMode":false,"pivot":{"x":546.0,"y":284.74639892578127,"z":0.0},"rotation":{"x":0.05544370785355568,"y":-0.7137016654014587,"z":0.05685894936323166,"w":0.6959362626075745},"size":0.8049487471580505,"orthographic":false}